collective.prometheus-1.6.0-py3.8-nspkg.pth
collective/__pycache__/__init__.cpython-37.pyc
collective/prometheus/__init__.py
collective/prometheus/__init__.pyc
collective/prometheus/browser.py
collective/prometheus/browser.pyc
collective/prometheus/configure.zcml
collective/prometheus/__pycache__/__init__.cpython-37.pyc
collective/prometheus/__pycache__/browser.cpython-37.pyc
collective.prometheus-1.6.0.dist-info/METADATA
collective.prometheus-1.6.0.dist-info/WHEEL
collective.prometheus-1.6.0.dist-info/entry_points.txt
collective.prometheus-1.6.0.dist-info/namespace_packages.txt
collective.prometheus-1.6.0.dist-info/top_level.txt
collective.prometheus-1.6.0.dist-info/RECORD
