Metadata-Version: 2.1
Name: collective.prometheus
Version: 1.6.0
Summary: Prometheus integration for Zope/Plone.
Home-page: https://github.com/collective/collective.prometheus
Author: Rob McBroom
Author-email: rob@sixfeetup.com
License: GPL
Keywords: plone zope prometheus monitoring
Platform: Any
Classifier: Programming Language :: Python
Classifier: Framework :: Plone
Classifier: Framework :: ZODB
Classifier: Framework :: Zope2
Classifier: Intended Audience :: Developers
Classifier: Intended Audience :: System Administrators
Classifier: Programming Language :: Python
Classifier: Topic :: System :: Networking :: Monitoring
Classifier: Topic :: Software Development :: Libraries :: Python Modules
Requires-Dist: setuptools
Provides-Extra: test
Requires-Dist: plone.app.testing ; extra == 'test'
Provides-Extra: zserver
Requires-Dist: Products.ZServerViews (>=0.2) ; extra == 'zserver'
